token_sub_info/__init__.py
token_sub_info/get_info.py
token_sub_info/utils.py
token_sub_info/exceptions/__init__.py
token_sub_info/exceptions/main_exceptions.py
token_sub_info/exceptions/sub_exceptions/__init__.py
token_sub_info/exceptions/sub_exceptions/forbidden_exceptions.py
token_sub_info/exceptions/sub_exceptions/not_found_exceptions.py
token_sub_info/exceptions/sub_exceptions/unauthorized_exceptions.py
token_sub_info/schemas/__init__.py
token_sub_info/schemas/schemas.py
token_sub_info-0.1.18.dist-info/METADATA
token_sub_info-0.1.18.dist-info/WHEEL
token_sub_info-0.1.18.dist-info/top_level.txt
token_sub_info-0.1.18.dist-info/RECORD
