Metadata-Version: 2.1
Name: token_sub_info
Version: 0.1.18
Summary: A library for extracting information from jwt tokens.
Author: Ilya Mikhasik
Author-email: imikhassik@gmail.com
Classifier: Programming Language :: Python :: 3
Classifier: Operating System :: OS Independent
Requires-Python: >=3.12
Requires-Dist: cryptography ==40.0.0
Requires-Dist: fastapi ==0.104.1
Requires-Dist: PyJWT ==2.8.0
